simple_dmarc_parser/__init__.py
simple_dmarc_parser/dmarc_parser.py
simple_dmarc_parser-1.1.0.dist-info/entry_points.txt
simple_dmarc_parser-1.1.0.dist-info/licenses/LICENSE
simple_dmarc_parser-1.1.0.dist-info/METADATA
simple_dmarc_parser-1.1.0.dist-info/WHEEL
simple_dmarc_parser-1.1.0.dist-info/RECORD
