Metadata-Version: 2.4
Name: simple-dmarc-parser
Version: 1.1.0
Summary: A Python script that processes DMARC reports from a mailbox and gives a basic summary.
License: MIT
License-File: LICENSE
Keywords: dmarc,rua
Author: FrostTheFox
Author-email: python@frostthefox.pw
Requires-Python: >=3.9
Classifier: License :: OSI Approved :: MIT License
Classifier: Programming Language :: Python :: 3
Classifier: Programming Language :: Python :: 3.9
Classifier: Programming Language :: Python :: 3.10
Classifier: Programming Language :: Python :: 3.11
Classifier: Programming Language :: Python :: 3.12
Classifier: Programming Language :: Python :: 3.13
Classifier: Programming Language :: Python :: 3.14
Requires-Dist: imap-tools (>=1.11.0,<2.0.0)
Requires-Dist: xmltodict (>=1.0.2,<2.0.0)
Project-URL: Homepage, https://github.com/FrostTheFox/simple-dmarc-parser
Project-URL: Repository, https://github.com/FrostTheFox/simple-dmarc-parser
